cis/__init__.py
cis/cis_main.py
cis/evaluate.py
cis/exceptions.py
cis/info.py
cis/logging.conf
cis/maths.py
cis/parse.py
cis/parse_datetime.py
cis/plugin.py
cis/stats.py
cis/time_util.py
cis/utils.py
cis/aggregation/__init__.py
cis/aggregation/collapse_kernels.py
cis/aggregation/gridded_collapsor.py
cis/aggregation/ungridded_aggregator.py
cis/collocation/__init__.py
cis/collocation/col.py
cis/collocation/col_framework.py
cis/collocation/col_implementations.py
cis/collocation/data_index.py
cis/collocation/gridded_interpolation.py
cis/collocation/haversinedistancekdtreeindex.py
cis/collocation/kdtree.py
cis/data_io/Coord.py
cis/data_io/__init__.py
cis/data_io/aeronet.py
cis/data_io/common_data.py
cis/data_io/data_reader.py
cis/data_io/data_writer.py
cis/data_io/gridded_data.py
cis/data_io/hdf.py
cis/data_io/hdf_sd.py
cis/data_io/hdf_vd.py
cis/data_io/hyperpoint.py
cis/data_io/hyperpoint_view.py
cis/data_io/netcdf.py
cis/data_io/ungridded_data.py
cis/data_io/write_netcdf.py
cis/data_io/products/AProduct.py
cis/data_io/products/CCI.py
cis/data_io/products/HadGEM.py
cis/data_io/products/MODIS.py
cis/data_io/products/NCAR_NetCDF_RAF.py
cis/data_io/products/__init__.py
cis/data_io/products/caliop.py
cis/data_io/products/cloudsat.py
cis/data_io/products/gridded_NetCDF.py
cis/data_io/products/products.py
cis/plotting/__init__.py
cis/plotting/comparativescatter.py
cis/plotting/contourplot.py
cis/plotting/formatted_plot.py
cis/plotting/genericplot.py
cis/plotting/heatmap.py
cis/plotting/histogram.py
cis/plotting/histogram2d.py
cis/plotting/lineplot.py
cis/plotting/plot.py
cis/plotting/scatterplot.py
cis/plotting/taylor.py
cis/plotting/raster/world.topo.bathy.200407.3x1350x675.png
cis/plotting/raster/world.topo.bathy.200407.3x2700x1350.png
cis/plotting/raster/world.topo.bathy.200407.3x5400x2700.png
cis/subsetting/__init__.py
cis/subsetting/subset.py
cis/test/__init__.py
cis/test/integration_test_data.py
cis/test/runner.py
cis/test/utils_for_testing.py
cis-1.7.8.dist-info/COPYING
cis-1.7.8.dist-info/COPYING.LESSER
cis-1.7.8.dist-info/METADATA
cis-1.7.8.dist-info/WHEEL
cis-1.7.8.dist-info/top_level.txt
cis-1.7.8.dist-info/RECORD
