Metadata-Version: 2.1
Name: cis
Version: 1.7.8
Summary: Community Intercomparison Suite
Home-page: http://www.cistools.net/
Maintainer: Philip Kershaw
Maintainer-email: Philip.Kershaw@stfc.ac.uk
Classifier: License :: OSI Approved :: GNU Lesser General Public License v3 or later (LGPLv3+)
Classifier: Topic :: Scientific/Engineering :: Atmospheric Science
Classifier: Topic :: Scientific/Engineering :: Visualization
Classifier: Environment :: Console
License-File: COPYING
License-File: COPYING.LESSER
Requires-Dist: matplotlib (>=2.0)
Requires-Dist: netcdf4 (>=1.0)
Requires-Dist: numpy
Requires-Dist: scipy (>=0.15.0)
Requires-Dist: scitools-iris (>=1.8.0)
Requires-Dist: psutil (>=2.0.0)
Requires-Dist: six
Provides-Extra: hdf
Requires-Dist: pyhdf (>=0.9.0) ; extra == 'hdf'
Provides-Extra: pandas
Requires-Dist: pandas ; extra == 'pandas'
